mantle_client/__init__.py
mantle_client/client.py
mantle_client-0.2.0.dist-info/METADATA
mantle_client-0.2.0.dist-info/WHEEL
mantle_client-0.2.0.dist-info/licenses/LICENSE
mantle_client-0.2.0.dist-info/RECORD
