Metadata-Version: 2.4
Name: mantle-client
Version: 0.2.0
Summary: Private insights from research data - Client
Author-email: SBV <secret@example.com>
License-File: LICENSE
Requires-Python: >=3.12
Requires-Dist: loguru>=0.7.2
Requires-Dist: pyjwt>=2.10.0
Requires-Dist: requests>=2.32.0
